README.rst
setup.cfg
setup.py
asexecutor.egg-info/PKG-INFO
asexecutor.egg-info/SOURCES.txt
asexecutor.egg-info/dependency_links.txt
asexecutor.egg-info/requires.txt
asexecutor.egg-info/top_level.txt
src/__init__.py
src/calculator.py
src/client.py
src/executor.py
src/job.py
src/schedulers.py
src/units.py