Metadata-Version: 2.1
Name: asexecutor
Version: 0.2
Summary: A convenient python library to execute ASE (Atomic Simulation Environment) calculators on clusters.
Home-page: https://github.com/efiminem/asexecutor
Author: Efim Mazhnik
Author-email: efimmazhnik@gmail.com
License: UNKNOWN
Download-URL: https://github.com/efiminem/asexecutor/archive/v0.2.zip
Platform: UNKNOWN
Classifier: Development Status :: 2 - Pre-Alpha
Classifier: License :: OSI Approved :: MIT License
Classifier: Programming Language :: Python :: 3
Classifier: Operating System :: OS Independent
